{
  "version": 1,
  "libraries": {
    "client": [

    ],
    "common": [
      {
        "name": "net.minecraft:launchwrapper:1.12"
      },
      {
        "name": "net.fabricmc:tiny-mappings-parser:0.2.2.14",
        "url": "https://maven.fabricmc.net/"
      },
      {
        "name": "net.fabricmc:sponge-mixin:0.9.4+mixin.0.8.2",
        "url": "https://maven.fabricmc.net/"
      },
      {
        "name": "net.fabricmc:tiny-remapper:0.4.2",
        "url": "https://maven.fabricmc.net/"
      },
      {
        "name": "net.fabricmc:access-widener:1.0.0",
        "url": "https://maven.fabricmc.net/"
      },
      {
        "name": "org.ow2.asm:asm:9.1",
        "url": "https://maven.fabricmc.net/"
      },
      {
        "name": "org.ow2.asm:asm-analysis:9.1",
        "url": "https://maven.fabricmc.net/"
      },
      {
        "name": "org.ow2.asm:asm-commons:9.1",
        "url": "https://maven.fabricmc.net/"
      },
      {
        "name": "org.ow2.asm:asm-tree:9.1",
        "url": "https://maven.fabricmc.net/"
      },
      {
        "name": "org.ow2.asm:asm-util:9.1",
        "url": "https://maven.fabricmc.net/"
      }
    ],
    "server": [
      {
        "_comment": "jimfs in fabric-server-launch requires guava on the system classloader",
        "name": "com.google.guava:guava:21.0",
        "url": "https://maven.fabricmc.net/"
      }
    ]
  },
  "mainClass": "net.minecraft.launchwrapper.Launch",
  "arguments": {
    "client": [

    ],
    "common": [

    ],
    "server": [

    ]
  },
  "launchwrapper": {
    "tweakers": {
      "client": [
        "net.fabricmc.loader.impl.game.minecraft.launchwrapper.FabricClientTweaker"
      ],
      "common": [
      ],
      "server": [
        "net.fabricmc.loader.impl.game.minecraft.launchwrapper.FabricServerTweaker"
      ]
    }
  }
}
